LICENSE
README.md
setup.py
setup_nogui.py
bin/jamstats-nogui
src/jamstats/__init__.py
src/jamstats/data/__init__.py
src/jamstats/data/game_data.py
src/jamstats/data/json_to_pandas.py
src/jamstats/io/__init__.py
src/jamstats/io/scoreboard_json_io.py
src/jamstats/io/scoreboard_server_io.py
src/jamstats/io/tsv_io.py
src/jamstats/plots/__init__.py
src/jamstats/plots/plot_together.py
src/jamstats/plots/plot_util.py
src/jamstats/resources/__init__.py
src/jamstats/util/__init__.py
src/jamstats/util/resources.py
src/jamstats/web/__init__.py
src/jamstats/web/statserver.py
src/jamstats_nogui.egg-info/PKG-INFO
src/jamstats_nogui.egg-info/SOURCES.txt
src/jamstats_nogui.egg-info/dependency_links.txt
src/jamstats_nogui.egg-info/requires.txt
src/jamstats_nogui.egg-info/top_level.txt